{
  "SN1": [
    {
      "CH1":{
        "port_1": 0,
        "port_2": 0,
        "port_3": 0,
        "port_4": 0,
        "port_5": 0,
        "port_6": 0
      },
      "CH2":{
        "port_1": 0,
        "port_2": 0,
        "port_3": 0,
        "port_4": 0,
        "port_5": 0,
        "port_6": 0
      },
      "CH3":{
        "port_1": 0,
        "port_2": 0,
        "port_3": 0,
        "port_4": 0,
        "port_5": 0,
        "port_6": 0
      },
      "CH4":{
        "port_1": 0,
        "port_2": 0,
        "port_3": 0,
        "port_4": 0,
        "port_5": 0,
        "port_6": 0
      }
    }
  ]
}